mvm_control.py
mvm_control-1.4.3.dist-info/entry_points.txt
mvm_control-1.4.3.dist-info/LICENSE
mvm_control-1.4.3.dist-info/WHEEL
mvm_control-1.4.3.dist-info/METADATA
mvm_control-1.4.3.dist-info/RECORD
