Metadata-Version: 2.1
Name: mvm-control
Version: 1.4.3
Summary: Simple command line tool to access a MVM ESP32 via the serial port
Home-page: https://github.com/MechanicalVentilatorMilano/mvm-control
License: GPL
Author: Bryerton Shaw
Author-email: bryerton@triumf.ca
Classifier: License :: OSI Approved :: GNU General Public License v3 or later (GPLv3+)
Requires-Dist: argparse
Requires-Dist: pyserial
Requires-Dist: paho-mqtt
Requires-Dist: requests
